dep_parsing_component/__init__.py
dep_parsing_component/frontend/build/asset-manifest.json
dep_parsing_component/frontend/build/bootstrap.min.css
dep_parsing_component/frontend/build/index.html
dep_parsing_component/frontend/build/precache-manifest.5b99ae620eab9fb79db13f3f9b11605d.js
dep_parsing_component/frontend/build/service-worker.js
dep_parsing_component/frontend/build/static/js/2.a1cc433f.chunk.js
dep_parsing_component/frontend/build/static/js/2.a1cc433f.chunk.js.LICENSE.txt
dep_parsing_component/frontend/build/static/js/2.a1cc433f.chunk.js.map
dep_parsing_component/frontend/build/static/js/main.ce3bc050.chunk.js
dep_parsing_component/frontend/build/static/js/main.ce3bc050.chunk.js.map
dep_parsing_component/frontend/build/static/js/runtime-main.11ec9aca.js
dep_parsing_component/frontend/build/static/js/runtime-main.11ec9aca.js.map
st_dep_parsing_component-0.0.3.dist-info/LICENSE
st_dep_parsing_component-0.0.3.dist-info/METADATA
st_dep_parsing_component-0.0.3.dist-info/WHEEL
st_dep_parsing_component-0.0.3.dist-info/top_level.txt
st_dep_parsing_component-0.0.3.dist-info/RECORD
