Metadata-Version: 2.1
Name: st-dep-parsing-component
Version: 0.0.3
Summary: UNKNOWN
Home-page: UNKNOWN
Author: yixiong321
Author-email: 
License: UNKNOWN
Platform: UNKNOWN
Requires-Python: >=3.6
Requires-Dist: streamlit (>=0.63)
